symcollab/algebra/__init__.py
symcollab/algebra/dag.py
symcollab/algebra/parser.py
symcollab/algebra/substitute.py
symcollab/algebra/sympy.py
symcollab/algebra/term.py
symcollab_algebra-0.1.1.dist-info/METADATA
symcollab_algebra-0.1.1.dist-info/WHEEL
symcollab_algebra-0.1.1.dist-info/top_level.txt
symcollab_algebra-0.1.1.dist-info/RECORD
