Metadata-Version: 2.1
Name: symcollab-algebra
Version: 0.1.1
Summary: UNKNOWN
Home-page: https://github.com/symcollab/cryptosolve
License: UNKNOWN
Platform: UNKNOWN
Requires-Dist: matplotlib (~=3.1.1)
Requires-Dist: mypy (~=0.740)
Requires-Dist: mypy-extensions (~=0.4.0)
Requires-Dist: networkx (~=2.3)
Requires-Dist: numpy (~=1.17.0)
Requires-Dist: sympy (==1.4)
